autoLIB/__init__.py
autoLIB/autoLIB.py
autoLIB/data/linguistic-category-model-lcm-dictionary.csv
autolib_psych-1.0.6.dist-info/licenses/LICENSE
autolib_psych-1.0.6.dist-info/METADATA
autolib_psych-1.0.6.dist-info/WHEEL
autolib_psych-1.0.6.dist-info/top_level.txt
autolib_psych-1.0.6.dist-info/RECORD
