Metadata-Version: 2.4
Name: autoLIB-psych
Version: 1.0.6
Summary: A Python package for automated detection of Linguistic Intergroup Bias (LIB) in text data using sentence-level sentiment and word-level abstraction analysis. Designed for research on language bias in news media and social discourse.
Author-email: "Ryan L. Boyd" <ryan@ryanboyd.io>
Project-URL: Homepage, https://github.com/ryanboyd/autoLIB
Project-URL: Issues, https://github.com/ryanboyd/autoLIB/issues
Classifier: Programming Language :: Python :: 3
Classifier: License :: OSI Approved :: MIT License
Classifier: Operating System :: OS Independent
Requires-Python: >=3.10
License-File: LICENSE
Requires-Dist: tqdm>=4.66.5
Requires-Dist: nltk>=3.9.1
Requires-Dist: stanza>=1.10.1
Requires-Dist: pandas>=2.2.3
Dynamic: license-file
